GSpreadPlus/__init__.py
GSpreadPlus/errors.py
GSpreadPlus/gspreadplus.py
GSpreadPlus/types.py
gspreadplus-0.5.1.dist-info/licenses/LICENSE
gspreadplus-0.5.1.dist-info/METADATA
gspreadplus-0.5.1.dist-info/WHEEL
gspreadplus-0.5.1.dist-info/top_level.txt
gspreadplus-0.5.1.dist-info/RECORD
