Metadata-Version: 2.4
Name: GSpreadPlus
Version: 0.5.1
Summary: A high-level wrapper library for Google Sheets API v4
Author-email: FishballNoodles <joelkhorxw@gmail.com>
License: MIT License
Project-URL: Homepage, https://github.com/TheReaper62/GSpread-Plus
Project-URL: Documentation, https://thereaper62.github.io/GSpread-Plus/documentation
Keywords: Google Spreadsheets,Sheets,Sheetsv4,google-spreadsheets
Classifier: Programming Language :: Python :: 3
Classifier: Operating System :: OS Independent
Requires-Python: >=3.8
License-File: LICENSE
Requires-Dist: gspread>=6.2.1
Dynamic: license-file
